[{"model": "main.articles", "pk": 4, "fields": {"image": "Exhibition_image/800x452_oonDMMG.webp", "name": "chess", "description": "", "image_1": "", "description_1": "", "image_2": "", "description_2": "", "image_3": "", "description_3": "daw", "image_4": "Exhibition_image/достоевскии__kplaMKU.jpeg", "category": 1}}, {"model": "main.articles", "pk": 5, "fields": {"image": "Exhibition_image/достоевскии__SsInjCM.jpeg", "name": "Культура", "description": "", "image_1": "", "description_1": "", "image_2": "", "description_2": "", "image_3": "", "description_3": "культура", "image_4": "Exhibition_image/достоевскии__OeZUsbe.jpeg", "category": 3}}, {"model": "main.articles", "pk": 6, "fields": {"image": "Exhibition_image/800x452_cut6x9r.webp", "name": "История", "description": "", "image_1": "", "description_1": "", "image_2": "", "description_2": "", "image_3": "", "description_3": "история", "image_4": "Exhibition_image/800x452_fYn4L4u.webp", "category": 2}}, {"model": "main.articles", "pk": 7, "fields": {"image": "Exhibition_image/большенадеюсь__mEd7wei.jpeg", "name": "Инновации", "description": "", "image_1": "", "description_1": "", "image_2": "", "description_2": "", "image_3": "", "description_3": "еще один", "image_4": "Exhibition_image/ещеодин_aYfFPik.jpeg", "category": 4}}, {"model": "main.articles", "pk": 8, "fields": {"image": "Exhibition_image/статуя_ч_и_д.jpeg", "name": "Семья", "description": "", "image_1": "", "description_1": "", "image_2": "", "description_2": "", "image_3": "", "description_3": "дауны", "image_4": "Exhibition_image/жузбаи.jpg", "category": 5}}, {"model": "main.articles", "pk": 9, "fields": {"image": "Exhibition_image/tantuni-logo3.jpg", "name": "Традиции", "description": "", "image_1": "", "description_1": "", "image_2": "", "description_2": "", "image_3": "", "description_3": "традиции", "image_4": "Exhibition_image/выставка1.jpeg", "category": 6}}, {"model": "main.articles", "pk": 10, "fields": {"image": "Exhibition_image/чокан_с_достоевским_.jpeg", "name": "архив", "description": "", "image_1": "", "description_1": "", "image_2": "", "description_2": "", "image_3": "", "description_3": "архив", "image_4": "Exhibition_image/чокан_с_достоевским__pu2p8pK.jpeg", "category": 7}}, {"model": "main.articles", "pk": 11, "fields": {"image": "Exhibition_image/fastback.jpeg", "name": "достопримечательности", "description": "", "image_1": "", "description_1": "", "image_2": "", "description_2": "", "image_3": "", "description_3": "достопримечательности", "image_4": "Exhibition_image/достоевскии__87h5Fyd.jpeg", "category": 8}}, {"model": "main.articles", "pk": 12, "fields": {"image": "Exhibition_image/большенадеюсь__BNxnIkf.jpeg", "name": "Худи черного цвета с монограммами adidas Originals", "description": "", "image_1": "", "description_1": "", "image_2": "", "description_2": "", "image_3": "", "description_3": "", "image_4": "", "category": 1}}, {"model": "main.articles", "pk": 13, "fields": {"image": "Exhibition_image/большенадеюсь__xjAkALW.jpeg", "name": "Худи черного цвета с монограммами adidas Originals", "description": "", "image_1": "", "description_1": "", "image_2": "", "description_2": "", "image_3": "", "description_3": "", "image_4": "", "category": 1}}, {"model": "main.articles", "pk": 14, "fields": {"image": "Exhibition_image/баг.jpg", "name": "Аксессуары", "description": "", "image_1": "", "description_1": "", "image_2": "", "description_2": "", "image_3": "", "description_3": "", "image_4": "", "category": 1}}]